Metadata-Version: 2.1
Name: biobuild
Version: 3.10.11
Summary: A fragment-based molecular assembly toolkit for python.
Home-page: https://github.com/NoahHenrikKleinschmidt/biobuild
Author: Noah H. Kleinschmidt
Author-email: noah.kleinschmidt@students.unibe.ch
Classifier: Programming Language :: Python :: 3
Classifier: License :: OSI Approved :: GNU General Public License v3 (GPLv3)
Classifier: Operating System :: OS Independent
Classifier: Topic :: Scientific/Engineering :: Bio-Informatics
Classifier: Topic :: Scientific/Engineering :: Chemistry
Requires-Python: >=3.10
License-File: LICENSE.md
